{
  "generatedAt": "2026-07-23T08:36:37.520Z",
  "definition": {
    "mode": "short",
    "selectionN": 100,
    "evaluationN": 1000,
    "selectionCandidates": 16,
    "evaluationSeedsAreHeldOut": true,
    "alumniChoicePolicies": [
      "teachAlways",
      "firstTeachThenMethod",
      "sayingsAlways",
      "methodAlways"
    ],
    "eventRule": "奇数月は必ずイベント1件。卒業生イベントは通常イベントを置き換え、大会は別枠",
    "caveat": "全行動列の数学的最適解ではなく、既知の強い4育成方針×4先輩方針の中での最良"
  },
  "cohorts": [
    {
      "background": "college",
      "difficulty": "ハード",
      "n": 1000,
      "candidate": {
        "trainPlan": "adaptive",
        "restLine": 55,
        "academic": "lean",
        "contestPolicy": "safe",
        "alumniChoice": "teachAlways",
        "id": "adaptive__rest55__lean__safe__teachAlways"
      },
      "rankCounts": {
        "S": 26,
        "A": 20,
        "B": 61,
        "C": 132,
        "D": 355,
        "E": 406,
        "退学": 0
      },
      "rankRates": {
        "S": 0.026,
        "A": 0.02,
        "B": 0.061,
        "C": 0.132,
        "D": 0.355,
        "E": 0.406,
        "退学": 0
      },
      "graduationRate": 1,
      "meanPoints": 230.314,
      "meanAbility": 57.85692307692312,
      "meanWins": 1.415,
      "meanPodiums": 2.499,
      "ajdcOverallWinRate": 0.019,
      "worldsQualifiedRate": 0.118,
      "worldsWinRate": 0.001,
      "meanAlumniEvents": 2,
      "techniqueRates": {
        "none": 0.012,
        "high_toss": 0.344,
        "fts": 0.311,
        "on_beat": 0.333
      },
      "selectionTop5": [
        {
          "candidate": {
            "trainPlan": "adaptive",
            "restLine": 55,
            "academic": "lean",
            "contestPolicy": "safe",
            "alumniChoice": "teachAlways",
            "id": "adaptive__rest55__lean__safe__teachAlways"
          },
          "meanPoints": 264.58
        },
        {
          "candidate": {
            "trainPlan": "adaptive",
            "restLine": 55,
            "academic": "lean",
            "contestPolicy": "adaptive",
            "alumniChoice": "firstTeachThenMethod",
            "id": "adaptive__rest55__lean__adaptive__firstTeachThenMethod"
          },
          "meanPoints": 248.34
        },
        {
          "candidate": {
            "trainPlan": "adaptive",
            "restLine": 55,
            "academic": "lean",
            "contestPolicy": "safe",
            "alumniChoice": "methodAlways",
            "id": "adaptive__rest55__lean__safe__methodAlways"
          },
          "meanPoints": 244.8
        },
        {
          "candidate": {
            "trainPlan": "adaptive",
            "restLine": 55,
            "academic": "lean",
            "contestPolicy": "adaptive",
            "alumniChoice": "methodAlways",
            "id": "adaptive__rest55__lean__adaptive__methodAlways"
          },
          "meanPoints": 241.45
        },
        {
          "candidate": {
            "trainPlan": "adaptive",
            "restLine": 55,
            "academic": "lean",
            "contestPolicy": "safe",
            "alumniChoice": "sayingsAlways",
            "id": "adaptive__rest55__lean__safe__sayingsAlways"
          },
          "meanPoints": 239.66
        }
      ]
    },
    {
      "background": "highschool",
      "difficulty": "ノーマル",
      "n": 1000,
      "candidate": {
        "trainPlan": "adaptive",
        "restLine": 55,
        "academic": "lean",
        "contestPolicy": "adaptive",
        "alumniChoice": "teachAlways",
        "id": "adaptive__rest55__lean__adaptive__teachAlways"
      },
      "rankCounts": {
        "S": 447,
        "A": 234,
        "B": 238,
        "C": 74,
        "D": 6,
        "E": 1,
        "退学": 0
      },
      "rankRates": {
        "S": 0.447,
        "A": 0.234,
        "B": 0.238,
        "C": 0.074,
        "D": 0.006,
        "E": 0.001,
        "退学": 0
      },
      "graduationRate": 1,
      "meanPoints": 914.447,
      "meanAbility": 79.74915384615396,
      "meanWins": 6.033,
      "meanPodiums": 11.916,
      "ajdcOverallWinRate": 0.23,
      "worldsQualifiedRate": 0.785,
      "worldsWinRate": 0.022,
      "meanAlumniEvents": 2,
      "techniqueRates": {
        "none": 0.023,
        "high_toss": 0.316,
        "fts": 0.34,
        "on_beat": 0.321
      },
      "selectionTop5": [
        {
          "candidate": {
            "trainPlan": "adaptive",
            "restLine": 55,
            "academic": "lean",
            "contestPolicy": "adaptive",
            "alumniChoice": "teachAlways",
            "id": "adaptive__rest55__lean__adaptive__teachAlways"
          },
          "meanPoints": 954.96
        },
        {
          "candidate": {
            "trainPlan": "adaptive",
            "restLine": 55,
            "academic": "lean",
            "contestPolicy": "adaptive",
            "alumniChoice": "firstTeachThenMethod",
            "id": "adaptive__rest55__lean__adaptive__firstTeachThenMethod"
          },
          "meanPoints": 927.04
        },
        {
          "candidate": {
            "trainPlan": "adaptive",
            "restLine": 55,
            "academic": "lean",
            "contestPolicy": "adaptive",
            "alumniChoice": "sayingsAlways",
            "id": "adaptive__rest55__lean__adaptive__sayingsAlways"
          },
          "meanPoints": 905.53
        },
        {
          "candidate": {
            "trainPlan": "adaptive",
            "restLine": 55,
            "academic": "lean",
            "contestPolicy": "attack",
            "alumniChoice": "methodAlways",
            "id": "adaptive__rest55__lean__attack__methodAlways"
          },
          "meanPoints": 899.63
        },
        {
          "candidate": {
            "trainPlan": "adaptive",
            "restLine": 55,
            "academic": "lean",
            "contestPolicy": "safe",
            "alumniChoice": "teachAlways",
            "id": "adaptive__rest55__lean__safe__teachAlways"
          },
          "meanPoints": 899.03
        }
      ]
    },
    {
      "background": "juniorhigh",
      "difficulty": "イージー",
      "n": 1000,
      "candidate": {
        "trainPlan": "adaptive",
        "restLine": 55,
        "academic": "lean",
        "contestPolicy": "adaptive",
        "alumniChoice": "methodAlways",
        "id": "adaptive__rest55__lean__adaptive__methodAlways"
      },
      "rankCounts": {
        "S": 544,
        "A": 236,
        "B": 160,
        "C": 52,
        "D": 8,
        "E": 0,
        "退学": 0
      },
      "rankRates": {
        "S": 0.544,
        "A": 0.236,
        "B": 0.16,
        "C": 0.052,
        "D": 0.008,
        "E": 0,
        "退学": 0
      },
      "graduationRate": 1,
      "meanPoints": 980.527,
      "meanAbility": 80.93515384615372,
      "meanWins": 6.895,
      "meanPodiums": 13.516,
      "ajdcOverallWinRate": 0.271,
      "worldsQualifiedRate": 0.813,
      "worldsWinRate": 0.034,
      "meanAlumniEvents": 2,
      "techniqueRates": {
        "none": 1,
        "high_toss": 0,
        "fts": 0,
        "on_beat": 0
      },
      "selectionTop5": [
        {
          "candidate": {
            "trainPlan": "adaptive",
            "restLine": 55,
            "academic": "lean",
            "contestPolicy": "adaptive",
            "alumniChoice": "methodAlways",
            "id": "adaptive__rest55__lean__adaptive__methodAlways"
          },
          "meanPoints": 1006.76
        },
        {
          "candidate": {
            "trainPlan": "adaptive",
            "restLine": 55,
            "academic": "lean",
            "contestPolicy": "adaptive",
            "alumniChoice": "sayingsAlways",
            "id": "adaptive__rest55__lean__adaptive__sayingsAlways"
          },
          "meanPoints": 996.22
        },
        {
          "candidate": {
            "trainPlan": "adaptive",
            "restLine": 55,
            "academic": "lean",
            "contestPolicy": "attack",
            "alumniChoice": "methodAlways",
            "id": "adaptive__rest55__lean__attack__methodAlways"
          },
          "meanPoints": 995.8
        },
        {
          "candidate": {
            "trainPlan": "adaptive",
            "restLine": 55,
            "academic": "lean",
            "contestPolicy": "attack",
            "alumniChoice": "firstTeachThenMethod",
            "id": "adaptive__rest55__lean__attack__firstTeachThenMethod"
          },
          "meanPoints": 990.76
        },
        {
          "candidate": {
            "trainPlan": "adaptive",
            "restLine": 55,
            "academic": "lean",
            "contestPolicy": "adaptive",
            "alumniChoice": "firstTeachThenMethod",
            "id": "adaptive__rest55__lean__adaptive__firstTeachThenMethod"
          },
          "meanPoints": 988.35
        }
      ]
    }
  ]
}
